superman/dana_numbers.txt
superman/dana.py
superman/__init__.py
superman/mp.py
superman/preprocess.py
superman/utils.py
superman/classifiers/perceptron.py
superman/classifiers/nearest_neighbor.py
superman/classifiers/__init__.py
superman/classifiers/gaussian.py
superman/classifiers/decision_tree.py
superman/classifiers/utils.py
superman/file_io/spc.py
superman/file_io/renishaw.py
superman/file_io/opus.py
superman/file_io/construct_utils.py
superman/file_io/bruker_raw.py
superman/file_io/WITec.py
superman/file_io/andor.py
superman/file_io/__init__.py
superman/file_io/rruff.py
superman/distance/_pdist.cpython-36m-x86_64-linux-gnu.so
superman/distance/pairwise_dists.py
superman/distance/common.cpython-36m-x86_64-linux-gnu.so
superman/distance/__init__.py
superman/distance/_traj.cpython-36m-x86_64-linux-gnu.so
superman/peaks/savitzky_golay.py
superman/peaks/wavelet.py
superman/peaks/bump_fit.py
superman/peaks/__init__.py
superman/peaks/derivative.py
superman/peaks/common.py
superman/peaks/threshold.py
superman/dataset/ds.py
superman/dataset/_search.py
superman/dataset/metadata.py
superman/dataset/ds_view.py
superman/dataset/__init__.py
superman/baseline/tophat.py
superman/baseline/median.py
superman/baseline/wavelet.py
superman/baseline/polyfit.py
superman/baseline/rubberband.py
superman/baseline/mario.py
superman/baseline/kajfosz_kwiatek.py
superman/baseline/dietrich.py
superman/baseline/airpls.py
superman/baseline/lsd.py
superman/baseline/__init__.py
superman/baseline/als.py
superman/baseline/ob.py
superman/baseline/common.py
superman/baseline/fabc.py
superman/baseline/mpls.py
superman/.libs/libgomp-3300acd3.so.1.0.0
superman-0.1.0.dist-info/RECORD
superman-0.1.0.dist-info/top_level.txt
superman-0.1.0.dist-info/WHEEL
superman-0.1.0.dist-info/DESCRIPTION.rst
superman-0.1.0.dist-info/metadata.json
superman-0.1.0.dist-info/METADATA
superman-0.1.0.data/scripts/plot_spectra.py
superman-0.1.0.data/scripts/convert_spectra.py
superman-0.1.0.data/scripts/baseline.py
