Metadata-Version: 1.0
Name: superman
Version: 0.1.0
Summary: Spectrum preprocessing machine.
Home-page: https://github.com/all-umass/superman
Author: CJ Carey
Author-email: perimosocordiae@gmail.com
License: MIT
Platform: UNKNOWN
